cstrstrdict.cpython-310-powerpc64le-linux-gnu.so
strstrdict.libs/libstdc++-1b005a64.so.6.0.28
strstrdict.libs/libgcc_s-a2b893f1.so.1
strstrdict/__init__.py
strstrdict/py.typed
strstrdict-0.0.2.dist-info/top_level.txt
strstrdict-0.0.2.dist-info/METADATA
strstrdict-0.0.2.dist-info/LICENSE
strstrdict-0.0.2.dist-info/RECORD
strstrdict-0.0.2.dist-info/WHEEL
