Metadata-Version: 2.1
Name: strstrdict
Version: 0.0.2
Summary: lower memory alternative to string-to-string dict
Home-page: https://github.com/edgarsi/strstrdict
Author: Edgars Irmejs
Author-email: edgars.irmejs@gmail.com
License: UNKNOWN
Keywords: dict,str,cache,memory,overhead,string,hash,drop-in,alternative,replacement,dictionary
Platform: UNKNOWN
Classifier: Programming Language :: Python :: 3
Classifier: License :: OSI Approved :: Apache Software License
Classifier: Operating System :: OS Independent
Classifier: Development Status :: 2 - Pre-Alpha
Classifier: Intended Audience :: Developers
Requires-Python: >3.5
License-File: LICENSE
Provides-Extra: benchmark
Requires-Dist: memory-profiler ; extra == 'benchmark'
Requires-Dist: tabulate ; extra == 'benchmark'
Requires-Dist: sqlitedict ; extra == 'benchmark'
Requires-Dist: gmpy2 ; extra == 'benchmark'
Provides-Extra: release
Requires-Dist: sphinx ; extra == 'release'
Requires-Dist: bumpversion ; extra == 'release'
Provides-Extra: test
Requires-Dist: pytest ; extra == 'test'
Requires-Dist: flake8 ; extra == 'test'
